{
    "courses": [
        {
            "id":1,
            "specialization": "هندسة البرمجيات",
            "university": "جامعة عمان العربية",
            "faculty":"كلية العلوم الحاسوبية",
            "hourly_fee_cat1": "60 د",
            "hourly_fee_cat2": "42 د",
            "hourly_fee_cat3": "21 د",
            "hourly_fee_cat4": "18 د",
            "registration_fee": "260 د",
            "years": 4,
            "area":"عمان",
            "min-mark":60
        },
        {
            "id":2,
            "specialization": "علم البيانات الذكاء الاصطناعي",
            "university": "جامعة عمان العربية",
            "faculty":"كلية العلوم الحاسوبية",
            "hourly_fee_cat1": "60 د",
            "hourly_fee_cat2": "42 د",
            "hourly_fee_cat3": "21 د",
            "hourly_fee_cat4": "18 د",
            "registration_fee": "260 د",
            "years": 4,
            "area":"عمان",
            "min-mark":60
        },
        {
            "id":3,
            "specialization": "علم الحاسوب",
            "university": "جامعة عمان العربية",
            "faculty":"كلية العلوم الحاسوبية",
            "hourly_fee_cat1": "60 د",
            "hourly_fee_cat2": "42 د",
            "hourly_fee_cat3": "21 د",
            "hourly_fee_cat4": "18 د",
            "registration_fee": "260 د",
            "years": 4,
            "area":"عمان",
            "min-mark":60
        },
        {   
            "id":4,
            "specialization": "الامن السيبراني ",
            "university": "جامعة عمان العربية",
            "faculty":"كلية العلوم الحاسوبية",
            "hourly_fee_cat1": "70 د",
            "hourly_fee_cat2": "42 د",
            "hourly_fee_cat3": "24.5 د",
            "hourly_fee_cat4": "21 د",
            "registration_fee": "260 د",
            "years": 4,
            "area":"عمان",
            "min-mark":60
        },  {
            "id":5,
            "specialization": "تربية خاصه",
            "university": "جامعة عمان العربية",
            "faculty":"كلية العلوم التربوية و النفسية",
            "hourly_fee_cat1": "60 د",
            "hourly_fee_cat2": "36 د",
            "hourly_fee_cat3": "21 د",
            "hourly_fee_cat4": "12 د",
            "registration_fee": "260 د",
            "years": 4,
            "area":"عمان",
            "min-mark":60
        },  {
            "id":6,
            "specialization": "إدارة الأعمال",
            "university": "جامعة عمان العربية",
            "faculty":"كلية الأعمال",
            "hourly_fee_cat1": "75 د",
            "hourly_fee_cat2": "41 د",
            "hourly_fee_cat3": "26 د",
            "hourly_fee_cat4": "15 د",
            "registration_fee": "260 د",
            "years": 4,
            "area":"عمان",
            "min-mark":60
        },  
        
        {
            "id":7,
            "specialization": "التمويل والمصارف",
            "university": "جامعة عمان العربية",
            "faculty":"كلية الأعمال",
            "hourly_fee_cat1": "60 د",
            "hourly_fee_cat2": "30 د",
            "hourly_fee_cat3": "21 د",
            "hourly_fee_cat4": "12 د",
            "registration_fee": "260 د",
            "years": 4,
            "area":"عمان",
            "min-mark":60
        }, 
        {
            "id":8,
            "specialization": "إدارة الموارد البشريه",
            "university": "جامعة عمان العربية",
            "faculty":"كلية الأعمال",
            "hourly_fee_cat1": "85 د",
            "hourly_fee_cat2": "43 د",
            "hourly_fee_cat3": "29.75 د",
            "hourly_fee_cat4": "17 د",
            "registration_fee": "260 د",
            "years": 4,
            "area":"عمان",
            "min-mark":60
        }, 
        {   
            "id":9,
            "specialization": "المحاسبه",
            "university": "جامعة عمان العربية",
            "faculty":"كلية الأعمال",
            "hourly_fee_cat1": "75 د",
            "hourly_fee_cat2": "45 د",
            "hourly_fee_cat3": "26.25 د",
            "hourly_fee_cat4": "15 د",
            "registration_fee": "260 د",
            "years": 4,
            "area":"عمان",
            "min-mark":60
        }, 
        {
            "id":10,
            "specialization": "نظم المعلومات الادارية",
            "university": "جامعة عمان العربية",
            "faculty":"كلية الأعمال",
            "hourly_fee_cat1": "70 د",
            "hourly_fee_cat2": "35 د",
            "hourly_fee_cat3": "24.5 د",
            "hourly_fee_cat4": "14 د",
            "registration_fee": "260 د",
            "years": 4,
            "area":"عمان",
            "min-mark":60
        },
        {
            "id":11,
            "specialization": "النسويق الرقمي",
            "university": "جامعة عمان العربية",
            "faculty":"كلية الأعمال",
            "hourly_fee_cat1": "60 د",
            "hourly_fee_cat2": "42 د",
            "hourly_fee_cat3": "30 د",
            "hourly_fee_cat4": "12 د",
            "registration_fee": "260 د",
            "years": 4,
            "area":"عمان",
            "min-mark":60
        }, 
         {
            "id":12,
            "specialization": "المحاسبه وقانون الاعمال",
            "university": "جامعة عمان العربية",
            "faculty":"كلية الأعمال",
            "hourly_fee_cat1": "75 د",
            "hourly_fee_cat2": "45 د",
            "hourly_fee_cat3": "26.25 د",
            "hourly_fee_cat4": "7.5 د",
            "registration_fee": "260 د",
            "years": 4,
            "area":"عمان",
            "min-mark":60
        }, 
         {
            "id":13,
            "specialization": "القانون ",
            "university": "جامعة عمان العربية",
            "faculty":"كلية القانون",
            "hourly_fee_cat1": "60 د",
            "hourly_fee_cat2": "30 د",
            "hourly_fee_cat3": "30 د",
            "hourly_fee_cat4": "18 د",
            "registration_fee": "260 د",
            "years": 4,
            "area":"عمان",
            "min-mark":65
        }, 
         {
            "id":14,
            "specialization": "اللغه الانجليزيه والترجمه",
            "university": "جامعة عمان العربية",
            "faculty":" كلية الاداب والعلوم",
            "hourly_fee_cat1": "60 د",
            "hourly_fee_cat2": "39 د",
            "hourly_fee_cat3": "21 د",
            "hourly_fee_cat4": "18 د",
            "registration_fee": "260 د",
            "years": 4,
            "area":"عمان",
            "min-mark":60
        }, 
         {
            "id":15,
            "specialization": "الرياضيات",
            "university": "جامعة عمان العربية",
            "faculty":"كلية الاداب والعلوم ",
            "hourly_fee_cat1": "50 د",
            "hourly_fee_cat2": "30 د",
            "hourly_fee_cat3": "17.5 د",
            "hourly_fee_cat4": "15 د",
            "registration_fee": "260 د",
            "years": 4,
            "area":"عمان",
            "min-mark":60
        }, {
            "id":16,
            "specialization": "الفقه والاصول",
            "university": "جامعة عمان العربية",
            "faculty":"كلية الشريعه ",
            "hourly_fee_cat1": "20 د",
            "hourly_fee_cat2": "12 د",
            "hourly_fee_cat3": "7 د",
            "hourly_fee_cat4": "2 د",
            "registration_fee": "260 د",
            "years": 4,
            "area":"عمان",
            "min-mark":75
        }, {
            "id":17,
            "specialization": "صيانة الطائرات",
            "university": "جامعة عمان العربية",
            "faculty":"كلية علوم الطيران ",
            "hourly_fee_cat1": "90 د",
            "hourly_fee_cat2": "81 د",
            "hourly_fee_cat3": "81 د",
            "hourly_fee_cat4": "67.5 د",
            "registration_fee": "260 د",
            "years": 4,
            "area":"عمان",
            "min-mark":60
        },
        {
            "id":18,
            "specialization": "علوم الكترونيات الطيران",
            "university": "جامعة عمان العربية",
            "faculty":"كلية علوم الطيران ",
            "hourly_fee_cat1": "90 د",
            "hourly_fee_cat2": "81 د",
            "hourly_fee_cat3": "81 د",
            "hourly_fee_cat4": "67.5 د",
            "registration_fee": "260 د",
            "years": 4,
            "area":"عمان",
            "min-mark":60
        }, 
        {
            "id":19,
            "specialization": "هندسة العمارة",
            "university": "جامعة عمان العربية",
            "faculty":"كلية الهندسة ",
            "hourly_fee_cat1": "90 د",
            "hourly_fee_cat2": "45 د",
            "hourly_fee_cat3": "31.5 د",
            "hourly_fee_cat4": "18 د",
            "registration_fee": "260 د",
            "years": 5,
            "area":"عمان",
            "min-mark":80
        },  
        {
            "id":20,
            "specialization": "الهندسة المدنية",
            "university": "جامعة عمان العربية",
            "faculty":"كلية الهندسة ",
            "hourly_fee_cat1": "90 د",
            "hourly_fee_cat2": "49.5 د",
            "hourly_fee_cat3": "31.5 د",
            "hourly_fee_cat4": "18 د",
            "registration_fee": "260 د",
            "years": 5,
            "area":"عمان",
            "min-mark":80
        },  
        {
            "id":21,
            "specialization": " هندسة الطاقة المتجددة ",
            "university": "جامعة عمان العربية",
            "faculty":"كلية الهندسة ",
            "hourly_fee_cat1": "90 د",
            "hourly_fee_cat2": "45 د",
            "hourly_fee_cat3": "31.5 د",
            "hourly_fee_cat4": "18 د",
            "registration_fee": "260 د",
            "years": 4,
            "area":"عمان",
            "min-mark":80
        }, 
        {
            "id":22,
            "specialization": " صيدلة",
            "university": "جامعة عمان العربية",
            "faculty":"كلية الصيدلة ",
            "hourly_fee_cat1": "90 د",
            "hourly_fee_cat2": "72 د",
            "hourly_fee_cat3": "58.5 د",
            "hourly_fee_cat4": "54 د",
            "registration_fee": "260 د",
            "years": 5,
            "area":"عمان",
            "min-mark":80
        },
        {
            "id":23,
            "specialization": " اللغة العربية وآدابها ",
            "university": "جامعة فيلادلفيا",
            "faculty":" كلية الآداب والعلوم التربوية ",
            "hourly_fee_cat1": "30 د",
            "hourly_fee_cat2": "30 د",
            "hourly_fee_cat3": "30 د",
            "hourly_fee_cat4": "30 د",
            "registration_fee": "370 د",
            "years": 4,
            "area":"عمان",
            "min-mark":60
        },
        {
            "id":24,
            "specialization": " اللغة الإنجليزية وآدابها ",
            "university": "جامعة فيلادلفيا",
            "faculty":" كلية الآداب والعلوم التربوية ",
            "hourly_fee_cat1": "60 د",
            "hourly_fee_cat2": "40 د",
            "hourly_fee_cat3": "40 د",
            "hourly_fee_cat4": "40 د",
            "registration_fee": "370 د",
            "years": 4,
            "area":"عمان",
            "min-mark":60
        },
        {
            "id":25,
            "specialization": " اللغة الصينية وآدابها ",
            "university": "جامعة فيلادلفيا",
            "faculty":" كلية الآداب والعلوم التربوية ",
            "hourly_fee_cat1": "40 د",
            "hourly_fee_cat2": "20 د",
            "hourly_fee_cat3": "20 د",
            "hourly_fee_cat4": "20 د",
            "registration_fee": "370 د",
            "years": 4,
            "area":"عمان",
            "min-mark":60
        },
        {
            "id":26,
            "specialization": " الإرشاد النفسي ",
            "university": "جامعة فيلادلفيا",
            "faculty":" كلية الآداب والعلوم التربوية ",
            "hourly_fee_cat1": "40 د",
            "hourly_fee_cat2": "40 د",
            "hourly_fee_cat3": "40 د",
            "hourly_fee_cat4": "40 د",
            "registration_fee": "370 د",
            "years": 4,
            "area":"عمان",
            "min-mark":60
        },
        {   
            "id":27,
            "specialization": " التكنولوجيا الحيوية وهندسة الجينات ",
            "university": "جامعة فيلادلفيا",
            "faculty":" كلية العلوم ",
            "hourly_fee_cat1": "60 د",
            "hourly_fee_cat2": "50 د",
            "hourly_fee_cat3": "50 د",
            "hourly_fee_cat4": "50 د",
        
            "registration_fee": "370 د",
            "years": 4,
            "area":"عمان",
            "min-mark":60
        },
        {
            "id":28,
            "specialization": " الرياضيات ",
            "university": "جامعة فيلادلفيا",
            "faculty":" كلية العلوم ",
            "hourly_fee_cat1": "30 د",
            "hourly_fee_cat2": "30 د",
            "hourly_fee_cat3": "30 د",
            "hourly_fee_cat4": "30 د",
            "registration_fee": "370 د",
            "years": 4,
            "area":"عمان",
            "min-mark":630
        },
        {
            "id":29,
            "specialization": " المحاسبة ",
            "university": "جامعة فيلادلفيا",
            "faculty":" كلية الأعمال ",
            "hourly_fee_cat1": "60 د",
            "hourly_fee_cat2": "40 د",
            "hourly_fee_cat3": "40 د",
            "hourly_fee_cat4": "40 د",
            "registration_fee": "370 د",
            "years": 4,
            "area":"عمان",
            "min-mark":60
        },
        {
            "id":30,
            "specialization": " إدارة الأعمال ",
            "university": "جامعة فيلادلفيا",
            "faculty":" كلية الأعمال ",
            "hourly_fee_cat1": "60 د",
            "hourly_fee_cat2": "40 د",
            "hourly_fee_cat3": "40 د",
            "hourly_fee_cat4": "40 د",
            "registration_fee": "370 د",
            "years": 4,
            "area":"عمان",
            "min-mark":60
        },
        {
            "id":31,
            "specialization": " التسويق الإلكتروني والتواصل الاجتماعي ",
            "university": "جامعة فيلادلفيا",
            "faculty":" كلية الأعمال ",
            "hourly_fee_cat1": "60 د",
            "hourly_fee_cat2": "40 د",
            "hourly_fee_cat3": "40 د",
            "hourly_fee_cat4": "40 د",
            "registration_fee": "370 د",
            "years": 4,
            "area":"عمان",
            "min-mark":60
        },
        {
            "id":32,
            "specialization": " إدارة المستشفيات ",
            "university": "جامعة فيلادلفيا",
            "faculty":" كلية الأعمال ",
            "hourly_fee_cat1": "60 د",
            "hourly_fee_cat2": "40 د",
            "hourly_fee_cat3": "40 د",
            "hourly_fee_cat4": "40 د",
            "registration_fee": "370 د",
            "years": 4,
            "area":"عمان",
            "min-mark":60
        },
        {
            "id":33,
            "specialization": " التكنولوجيا المالية ",
            "university": "جامعة فيلادلفيا",
            "faculty":" كلية الأعمال ",
            "hourly_fee_cat1": "60 د",
            "hourly_fee_cat2": "40 د",
            "hourly_fee_cat3": "40 د",
            "hourly_fee_cat4": "40 د",
            "registration_fee": "370 د",
            "years": 4,
            "area":"عمان",
            "min-mark":60
        },
        {
            "id":34,
            "specialization": " الحقوق ",
            "university": "جامعة فيلادلفيا",
            "faculty":" كلية الحقوق ",
            "hourly_fee_cat1": "40 د",
            "hourly_fee_cat2": "40 د",
            "hourly_fee_cat3": "40 د",
            "hourly_fee_cat4": "40 د",
            "registration_fee": "370 د",
            "years": 4,
            "area":"عمان",
            "min-mark":65
        },
        {
            "id":35,
            "specialization": " الصيدلة ",
            "university": "جامعة فيلادلفيا",
            "faculty":" كلية الصيدلة ",
            "hourly_fee_cat1": "95 د",
            "hourly_fee_cat2": "80 د",
            "hourly_fee_cat3": "80 د",
            "hourly_fee_cat4": "80 د",
            "registration_fee": "370 د",
            "years": 4,
            "area":"عمان",
            "min-mark":80
        },
        {
            "id":36,
            "specialization": " الهندسة الكهربائية ",
            "university": "جامعة فيلادلفيا",
            "faculty":" كلية الهندسة والتكنولوجيا ",
            "hourly_fee_cat1": "85 د",
            "hourly_fee_cat2": "60 د",
            "hourly_fee_cat3": "60 د",
            "hourly_fee_cat4": "60 د",
            "registration_fee": "370 د",
            "years": 5,
            "area":"عمان",
            "min-mark":80
        },
        {
            "id":37,
            "specialization": "هندسة الطاقة المتجددة ",
            "university": "جامعة فيلادلفيا",
            "faculty":"كلية الهندسة والتكنولوجيا  ",
            "hourly_fee_cat1": "85 د",
            "hourly_fee_cat2": "60 د",
            "hourly_fee_cat3": "60 د",
            "hourly_fee_cat4": "60 د",
            "registration_fee": "370 د",
            "years": 5,
            "area":"عمان",
            "min-mark":80
        },
        {
            "id":38,
            "specialization": " الهندسة الميكانيكية ",
            "university": "جامعة فيلادلفيا",
            "faculty":" كلية الهندسة والتكنولوجيا ",
            "hourly_fee_cat1": "85 د",
            "hourly_fee_cat2": "60 د",
            "hourly_fee_cat3": "60 د",
            "hourly_fee_cat4": "60 د",
            "registration_fee": "370 د",
            "years": 5,
            "area":"عمان",
            "min-mark":80
        },
        {
            "id":39,
            "specialization": " هندسة الميكاترونيكس ",
            "university": "جامعة فيلادلفيا",
            "faculty":" كلية الهندسة والتكنولوجيا ",
            "hourly_fee_cat1": "75 د",
            "hourly_fee_cat2": "60 د",
            "hourly_fee_cat3": "60 د",
            "hourly_fee_cat4": "60 د",
            "registration_fee": "370 د",
            "years": 5,
            "area":"عمان",
            "min-mark":80
        },
        {
            "id":40,
            "specialization": " الهندسة المدنية  ",
            "university": "جامعة فيلادلفيا",
            "faculty":" كلية الهندسة والتكنولوجيا ",
            "hourly_fee_cat1": "95 د",
            "hourly_fee_cat2": "60 د",
            "hourly_fee_cat3": "60 د",
            "hourly_fee_cat4": "60 د",
            "registration_fee": "370 د",
            "years": 5,
            "area":"عمان",
            "min-mark":80
        },
        {
            "id":41,
            "specialization": " علم حاسوب ",
            "university": "جامعة فيلادلفيا",
            "faculty":" كلية تكنولوجيا المعلومات ",
            "hourly_fee_cat1": "70 د",
            "hourly_fee_cat2": "50 د",
            "hourly_fee_cat3": "50 د",
            "hourly_fee_cat4": "50 د",
            "registration_fee": "370 د",
            "years": 4,
            "area":"عمان",
            "min-mark":60
        },
        {
            "id":42,
            "specialization": " هندسة البرمجيات ",
            "university": "جامعة فيلادلفيا",
            "faculty":" كلية تكنولوجيا المعلومات ",
            "hourly_fee_cat1": "70 د",
            "hourly_fee_cat2": "50 د",
            "hourly_fee_cat3": "50 د",
            "hourly_fee_cat4": "50 د",
            "registration_fee": "370 د",
            "years": 4,
            "area":"عمان",
            "min-mark":60
        },
        {
            "id":43,
            "specialization": " أمن المعلومات والفضاء السيبراني ",
            "university": "جامعة فيلادلفيا",
            "faculty":" كلية تكنولوجيا المعلومات ",
            "hourly_fee_cat1": "70 د",
            "hourly_fee_cat2": "50 د",
            "hourly_fee_cat3": "50 د",
            "hourly_fee_cat4": "50 د",
            "registration_fee": "370 د",
            "years": 4,
            "area":"عمان",
            "min-mark":60
        }
        ,        
          {
            "id":44,
            "specialization": " علم البيانات والذكاء الاصطناعي ",
            "university": "جامعة فيلادلفيا",
            "faculty":" كلية تكنولوجيا المعلومات ",
            "hourly_fee_cat1": "70 د",
            "hourly_fee_cat2": "50 د",
            "hourly_fee_cat3": "50 د",
            "hourly_fee_cat4": "50 د",
            "registration_fee": "370 د",
            "years": 4,
            "area":"عمان",
            "min-mark":60
        },
        {
            "id":45,
            "specialization": " التمرسض ",
            "university": "جامعة فيلادلفيا",
            "faculty":" كلية التمريض ",
            "hourly_fee_cat1": "50 د",
            "hourly_fee_cat2": "50 د",
            "hourly_fee_cat3": "50 د",
            "hourly_fee_cat4": "50 د",
            "registration_fee": "370 د",
            "years": 4,
            "area":"عمان",
            "min-mark":70
        },
        {
            "id":46,
            "specialization": " العلاج الطبيعي ",
            "university": "جامعة فيلادلفيا",
            "faculty":" كلية العلوم الطبية المساندة ",
            "hourly_fee_cat1": "75 د",
            "hourly_fee_cat2": "50 د",
            "hourly_fee_cat3": "50 د",
            "hourly_fee_cat4": "50 د",
            "registration_fee": "370 د",
            "years": 4,
            "area":"عمان",
            "min-mark":70
        },
        {
            "id":47,
            "specialization": " التغذية السريرسة والحميات ",
            "university": "جامعة فيلادلفيا",
            "faculty":" كلية العلوم الطبية المساندة ",
            "hourly_fee_cat1": "75 د",
            "hourly_fee_cat2": "50 د",
            "hourly_fee_cat3": "50 د",
            "hourly_fee_cat4": "50 د",
            "registration_fee": "370 د",
            "years": 4,
            "area":"عمان",
            "min-mark":70
        },
        {
            "id":48,
            "specialization": " هندسة العمارة ",
            "university": "جامعة فيلادلفيا",
            "faculty":" كلية العمارة والتصميم ",
            "hourly_fee_cat1": "95 د",
            "hourly_fee_cat2": "60 د",
            "hourly_fee_cat3": "60 د",
            "hourly_fee_cat4": "60 د",
            "registration_fee": "370 د",
            "years": 5,
            "area":"عمان",
            "min-mark":80
        },
        {
            "id":49,
            "specialization": " التصميم الداخلي ",
            "university": "جامعة فيلادلفيا",
            "faculty":" كلية العمارة والتصميم ",
            "hourly_fee_cat1": "70 د",
            "hourly_fee_cat2": "60 د",
            "hourly_fee_cat3": "60 د",
            "hourly_fee_cat4": "60 د",
        
            "registration_fee": "370 د",
            "years": 4,
            "area":"عمان",
            "min-mark":60
        },
        {
            "id":50,
            "specialization": " التحريك والوسائط المتعددة ",
            "university": "جامعة فيلادلفيا",
            "faculty":" كلية العمارة والتصميم ",
            "hourly_fee_cat1": "70 د",
            "hourly_fee_cat2": "40 د",
            "hourly_fee_cat3": "40 د",
            "hourly_fee_cat4": "40 د",
        
            "registration_fee": "370 د",
            "years": 4,
            "area":"عمان",
            "min-mark":60
        },
        {
            "id": 51,
            "specialization": " اللغة الإنجليزية وآدابها ",
            "university": "جامعة الشرق الاوسط ",
            "faculty": " كلية الآداب والعلوم التربوية ",
            "hourly_fee_cat1": "80 د",
            "hourly_fee_cat2": "80 د",
            "hourly_fee_cat3": "80 د",
            "hourly_fee_cat4": "80 د",
            "registration_fee": "450 د",
            "years": 4,
            "area": "عمان",
            "min-mark": 60
        },
        {
            "id": 52,
            "specialization": " اللغة العربية وآدابها ",
            "university": "جامعة الشرق الاوسط ",
            "faculty": " كلية الآداب والعلوم التربوية ",
            "hourly_fee_cat1": "45 د",
            "hourly_fee_cat2": "45 د",
            "hourly_fee_cat3": "45 د",
            "hourly_fee_cat4": "45 د",
            "registration_fee": "450 د",
            "years": 4,
            "area": "عمان",
            "min-mark": 60
        },
        {
            "id": 53,
            "specialization": " الترجمة التطبيقية ",
            "university": "جامعة الشرق الاوسط ",
            "faculty": " كلية الآداب والعلوم التربوية ",
            "hourly_fee_cat1": "90 د",
            "hourly_fee_cat2": "90 د",
            "hourly_fee_cat3": "90 د",
            "hourly_fee_cat4": "90 د",
            "registration_fee": "450 د",
            "years": 4,
            "area": "عمان",
            "min-mark": 60
        },
        {
            "id": 54,
            "specialization": " تكنولوجيا التعليم ",
            "university": "جامعة الشرق الاوسط ",
            "faculty": " كلية الآداب والعلوم التربوية ",
            "hourly_fee_cat1": "70 د",
            "hourly_fee_cat2": "70 د",
            "hourly_fee_cat3": "70 د",
            "hourly_fee_cat4": "70 د",
            "registration_fee": "450 د",
            "years": 4,
            "area": "عمان",
            "min-mark": 60
        },
        {
            "id": 55,
            "specialization": " القانون ",
            "university": "جامعة الشرق الاوسط ",
            "faculty": " كلية الحقوق ",
            "hourly_fee_cat1": "65 د",
            "hourly_fee_cat2": "65 د",
            "hourly_fee_cat3": "65 د",
            "hourly_fee_cat4": "65 د",
            "registration_fee": "450 د",
            "years": 4,
            "area": "عمان",
            "min-mark": 65
        },
        {
            "id": 56,
            "specialization": " إدارة الأعمال ",
            "university": "جامعة الشرق الاوسط ",
            "faculty": " كلية الأعمال ",
            "hourly_fee_cat1": "80 د",
            "hourly_fee_cat2": "80 د",
            "hourly_fee_cat3": "80 د",
            "hourly_fee_cat4": "80 د",
            "registration_fee": "450 د",
            "years": 4,
            "area": "عمان",
            "min-mark": 60
        },
        {
            "id": 57,
            "specialization": " التسويق الإلكتروني والتواصل الإجتماعي ",
            "university": "جامعة الشرق الاوسط ",
            "faculty": " كلية الأعمال ",
            "hourly_fee_cat1": "90 د",
            "hourly_fee_cat2": "90 د",
            "hourly_fee_cat3": "90 د",
            "hourly_fee_cat4": "90 د",
            "registration_fee": "450 د",
            "years": 4,
            "area": "عمان",
            "min-mark": 60
        },
        {
            "id": 58,
            "specialization": " ذكاء الأعمال ",
            "university": "جامعة الشرق الاوسط ",
            "faculty": " كلية الأعمال ",
            "hourly_fee_cat1": "90 د",
            "hourly_fee_cat2": "90 د",
            "hourly_fee_cat3": "90 د",
            "hourly_fee_cat4": "90 د",
            "registration_fee": "450 د",
            "years": 4,
            "area": "عمان",
            "min-mark": 60
        },
        {
            "id": 59,
            "specialization": " التكنولوجيا المالية ",
            "university": "جامعة الشرق الاوسط ",
            "faculty": " كلية الأعمال ",
            "hourly_fee_cat1": "90 د",
            "hourly_fee_cat2": "90 د",
            "hourly_fee_cat3": "90 د",
            "hourly_fee_cat4": "90 د",
            "registration_fee": "450 د",
            "years": 4,
            "area": "عمان",
            "min-mark": 60
        },
        {
            "id": 60,
            "specialization": " المحاسبة ",
            "university": "جامعة الشرق الاوسط ",
            "faculty": " كلية الأعمال ",
            "hourly_fee_cat1": "85 د",
            "hourly_fee_cat2": "85 د",
            "hourly_fee_cat3": "85 د",
            "hourly_fee_cat4": "85 د",
            "registration_fee": "450 د",
            "years": 4,
            "area": "عمان",
            "min-mark": 60
        },
        {
            "id": 61,
            "specialization": " الاعمال والتجارة الالكترونية ",
            "university": "جامعة الشرق الاوسط ",
            "faculty": " كلية الأعمال ",
            "hourly_fee_cat1": "90 د",
            "hourly_fee_cat2": "90 د",
            "hourly_fee_cat3": "90 د",
            "hourly_fee_cat4": "90 د",
            "registration_fee": "450 د",
            "years": 4,
            "area": "عمان",
            "min-mark": 60
        },
        {
            "id": 62,
            "specialization": " إدارة سلسلة التوريد والإدارة اللوجيستية الرقمية ",
            "university": "جامعة الشرق الاوسط ",
            "faculty": " كلية الأعمال ",
            "hourly_fee_cat1": "90 د",
            "hourly_fee_cat2": "90 د",
            "hourly_fee_cat3": "90 د",
            "hourly_fee_cat4": "90 د",
            "registration_fee": "450 د",
            "years": 4,
            "area": "عمان",
            "min-mark": 60
        },
        {
            "id": 63,
            "specialization": " علم الحاسوب ",
            "university": "جامعة الشرق الاوسط ",
            "faculty": " كلية تكنولوجيا المعلومات ",
            "hourly_fee_cat1": "80 د",
            "hourly_fee_cat2": "80 د",
            "hourly_fee_cat3": "80 د",
            "hourly_fee_cat4": "80 د",
            "registration_fee": "450 د",
            "years": 4,
            "area": "عمان",
            "min-mark": 60
        },
        {
            "id": 64,
            "specialization": " الذكاء الإصطناعي ",
            "university": "جامعة الشرق الاوسط ",
            "faculty": " كلية تكنولوجيا المعلومات ",
            "hourly_fee_cat1": "100 د",
            "hourly_fee_cat2": "100 د",
            "hourly_fee_cat3": "100 د",
            "hourly_fee_cat4": "100 د",
            "registration_fee": "450 د",
            "years": 4,
            "area": "عمان",
            "min-mark": 60
        },
        {
            "id": 65,
            "specialization": " هندسة البرمجيات ",
            "university": "جامعة الشرق الاوسط ",
            "faculty": " كلية تكنولوجيا المعلومات ",
            "hourly_fee_cat1": "90 د",
            "hourly_fee_cat2": "90 د",
            "hourly_fee_cat3": "90 د",
            "hourly_fee_cat4": "90 د",
            "registration_fee": "450 د",
            "years": 4,
            "area": "عمان",
            "min-mark": 60
        },
        {
            "id": 66,
            "specialization": " الأمن السيبراني ",
            "university": "جامعة الشرق الاوسط ",
            "faculty": " كلية تكنولوجيا المعلومات ",
            "hourly_fee_cat1": "90 د",
            "hourly_fee_cat2": "90 د",
            "hourly_fee_cat3": "90 د",
            "hourly_fee_cat4": "90 د",
            "registration_fee": "450 د",
            "years": 4,
            "area": "عمان",
            "min-mark": 60
        },
        {
            "id": 67,
            "specialization": " الهندسة المدنية ",
            "university": "جامعة الشرق الاوسط ",
            "faculty": " كلية الهندسة ",
            "hourly_fee_cat1": "110 د",
            "hourly_fee_cat2": "110 د",
            "hourly_fee_cat3": "110 د",
            "hourly_fee_cat4": "110 د",
            "registration_fee": "450 د",
            "years": 5,
            "area": "عمان",
            "min-mark": 80
        },
        {
            "id": 68,
            "specialization": " هندسة الطاقة المتجددة ",
            "university": "جامعة الشرق الاوسط ",
            "faculty": " كلية الهندسة ",
            "hourly_fee_cat1": "110 د",
            "hourly_fee_cat2": "110 د",
            "hourly_fee_cat3": "110 د",
            "hourly_fee_cat4": "110 د",
            "registration_fee": "450 د",
            "years": 5,
            "area": "عمان",
            "min-mark": 80
        },
        {
            "id": 69,
            "specialization": " هندسة الانظمة الذكية ",
            "university": "جامعة الشرق الاوسط ",
            "faculty": " كلية الهندسة ",
            "hourly_fee_cat1": "110 د",
            "hourly_fee_cat2": "110 د",
            "hourly_fee_cat3": "110 د",
            "hourly_fee_cat4": "110 د",
            "registration_fee": "450 د",
            "years": 5,
            "area": "عمان",
            "min-mark": 80
        },
        {
            "id": 70,
            "specialization": " الصحافة والإعلام ",
            "university": "جامعة الشرق الاوسط ",
            "faculty": " كلية الإعلام ",
            "hourly_fee_cat1": "70 د",
            "hourly_fee_cat2": "70 د",
            "hourly_fee_cat3": "70 د",
            "hourly_fee_cat4": "70 د",
            "registration_fee": "450 د",
            "years": 4,
            "area": "عمان",
            "min-mark": 60
        },
        {
            "id": 71,
            "specialization": " الإذاعة والتلفزيون ",
            "university": "جامعة الشرق الاوسط ",
            "faculty": " كلية الإعلام ",
            "hourly_fee_cat1": "70 د",
            "hourly_fee_cat2": "70 د",
            "hourly_fee_cat3": "70 د",
            "hourly_fee_cat4": "70 د",
            "registration_fee": "450 د",
            "years": 4,
            "area": "عمان",
            "min-mark": 60
        },
        {
            "id": 72,
            "specialization": " الإعلام الرقمي ",
            "university": "جامعة الشرق الاوسط ",
            "faculty": " كلية الإعلام ",
            "hourly_fee_cat1": "80 د",
            "hourly_fee_cat2": "80 د",
            "hourly_fee_cat3": "80 د",
            "hourly_fee_cat4": "80 د",
            "registration_fee": "450 د",
            "years": 4,
            "area": "عمان",
            "min-mark": 60
        },
        {
            "id": 73,
            "specialization": " هندسة العمارة ",
            "university": "جامعة الشرق الاوسط ",
            "faculty": " كلية العمارة والتصميم ",
            "hourly_fee_cat1": "110 د",
            "hourly_fee_cat2": "110 د",
            "hourly_fee_cat3": "110 د",
            "hourly_fee_cat4": "110 د",
            "registration_fee": "450 د",
            "years": 5,
            "area": "عمان",
            "min-mark": 80
        },
        {
            "id": 74,
            "specialization": " التصميم الجرافيكي ",
            "university": "جامعة الشرق الاوسط ",
            "faculty": " كلية العمارة والتصميم ",
            "hourly_fee_cat1": "90 د",
            "hourly_fee_cat2": "90 د",
            "hourly_fee_cat3": "90 د",
            "hourly_fee_cat4": "90 د",
            "registration_fee": "450 د",
            "years": 4,
            "area": "عمان",
            "min-mark": 60
        },
        {
            "id": 75,
            "specialization": " التصميم الداخلي ",
            "university": "جامعة الشرق الاوسط ",
            "faculty": " كلية العمارة والتصميم ",
            "hourly_fee_cat1": "100 د",
            "hourly_fee_cat2": "100 د",
            "hourly_fee_cat3": "100 د",
            "hourly_fee_cat4": "100 د",
            "registration_fee": "450 د",
            "years": 4,
            "area": "عمان",
            "min-mark": 60
        },
        {
            "id": 76,
            "specialization": " الصيدلة ",
            "university": "جامعة الشرق الاوسط ",
            "faculty": " كلية الصيدلة ",
            "hourly_fee_cat1": "130 د",
            "hourly_fee_cat2": "130 د",
            "hourly_fee_cat3": "130 د",
            "hourly_fee_cat4": "130 د",
            "registration_fee": "450 د",
            "years": 5,
            "area": "عمان",
            "min-mark": 80
        },
        {
            "id": 77,
            "specialization": " تصنيع المستحضرات التجميلية والكيماوية ",
            "university": "جامعة الشرق الاوسط ",
            "faculty": " كلية الصيدلة ",
            "hourly_fee_cat1": "100 د",
            "hourly_fee_cat2": "100 د",
            "hourly_fee_cat3": "100 د",
            "hourly_fee_cat4": "100 د",
            "registration_fee": "450 د",
            "years": 4,
            "area": "عمان",
            "min-mark": 70
        },
        {
            "id": 78,
            "specialization": " العلاج الطبيعي ",
            "university": "جامعة الشرق الاوسط ",
            "faculty": " كلية العلوم الطبية المساندة ",
            "hourly_fee_cat1": "100 د",
            "hourly_fee_cat2": "100 د",
            "hourly_fee_cat3": "100 د",
            "hourly_fee_cat4": "100 د",
            "registration_fee": "450 د",
            "years": 4,
            "area": "عمان",
            "min-mark": 70
        },
        {
            "id": 79,
            "specialization": " التمريض ",
            "university": "جامعة الشرق الاوسط ",
            "faculty": " كلية التمريض ",
            "hourly_fee_cat1": "85 د",
            "hourly_fee_cat2": "85 د",
            "hourly_fee_cat3": "85 د",
            "hourly_fee_cat4": "85 د",
            "registration_fee": "450 د",
            "years": 4,
            "area": "عمان",
            "min-mark": 70
        }
    ]
}